README.md
setup.py
davinci/__init__.py
davinci/cervix_problem.py
davinci/cifar_problem.py
davinci/cifar_small_problem.py
davinci/datasets.py
davinci/imagenet_problem.py
davinci/kdd_protein_problem.py
davinci/mnist_problem.py
davinci/pascal_alpha_problem.py
davinci/ptblm_problem.py
davinci/six_problem.py
davinci/snli_problem.py
davinci/tiny_imagenet_problem.py
davinci/utils.py
davinci/vae_problem.py
davinci/wikitext2_problem.py
davinci.egg-info/PKG-INFO
davinci.egg-info/SOURCES.txt
davinci.egg-info/dependency_links.txt
davinci.egg-info/top_level.txt